django_shared_session-0.4.0.dist-info/METADATA
django_shared_session-0.4.0.dist-info/RECORD
django_shared_session-0.4.0.dist-info/WHEEL
django_shared_session-0.4.0.dist-info/top_level.txt
shared_session/__init__.py
shared_session/signals.py
shared_session/views.py
shared_session/templatetags/__init__.py
shared_session/templatetags/shared_session.py
