Metadata-Version: 2.1
Name: django-shared-session
Version: 0.4.0
Summary: Django session sharing across multiple domains running same application
Home-page: https://github.com/ViktorStiskala/django-shared-session
Author: Viktor Stískala
Author-email: viktor@stiskala.cz
License: MPL
Platform: UNKNOWN
Classifier: Intended Audience :: Developers
Classifier: Operating System :: OS Independent
Classifier: Programming Language :: Python
Classifier: Programming Language :: Python :: 3 :: Only
Classifier: Topic :: Software Development :: Libraries
Classifier: Topic :: Software Development :: Libraries :: Python Modules
Requires-Dist: setuptools-git
Requires-Dist: django (>=1.7)
Requires-Dist: python-dateutil (>=2.5)
Requires-Dist: PyNaCl (>=1.0.0)
